dcm2niixpy/__init__.py
dcm2niixpy/dcm2niix.py
dcm2niixpy-1.1.0.dist-info/LICENSE
dcm2niixpy-1.1.0.dist-info/WHEEL
dcm2niixpy-1.1.0.dist-info/METADATA
dcm2niixpy-1.1.0.dist-info/RECORD
